README.rst
setup.py
flask_json_api/__init__.py
flask_json_api.egg-info/PKG-INFO
flask_json_api.egg-info/SOURCES.txt
flask_json_api.egg-info/dependency_links.txt
flask_json_api.egg-info/not-zip-safe
flask_json_api.egg-info/requires.txt
flask_json_api.egg-info/top_level.txt