Metadata-Version: 1.1
Name: flask-json-api
Version: 1.0.0
Summary: ['The Flask JSON API package provides boilerplate code for setting up REST based apps.']
Home-page: https://gitlab.com/py-ddd/flask-json-api
Author: Victor Klapholz
Author-email: victor.klapholz@gmail.com
License: MIT
Keywords: flask,rest,json,api,content-type,exception
Platform: UNKNOWN
Classifier: Development Status :: 5 - Production/Stable
Classifier: Intended Audience :: Developers
Classifier: License :: OSI Approved :: MIT License
Classifier: Programming Language :: Python :: 3.6
Classifier: Programming Language :: Python :: Implementation :: CPython
Classifier: Programming Language :: Python :: Implementation :: PyPy
